datarade/__init__.py
datarade/git_client.py
datarade/models.py
datarade/schemas.py
datarade/services.py
datarade-0.3.0.dist-info/LICENSE
datarade-0.3.0.dist-info/WHEEL
datarade-0.3.0.dist-info/METADATA
datarade-0.3.0.dist-info/RECORD
