Metadata-Version: 2.1
Name: datarade
Version: 0.3.0
Summary: This library provides tools that allow datasets to be defined separately from a pipeline.
Home-page: https://github.com/fivestack/datarade
License: UNKNOWN
Keywords: datarade mssql database data pipeline
Author: Mike Alfare
Author-email: alfare@gmail.com
Requires-Python: >=3.7,<4.0
Classifier: Development Status :: 4 - Beta
Classifier: License :: OSI Approved :: Apache Software License
Classifier: Programming Language :: Python :: 3.7
Classifier: Operating System :: Microsoft :: Windows
Classifier: Topic :: Database
Requires-Dist: marshmallow>=3.4,<4.0
Requires-Dist: pyyaml>=5.1,<6.0
Requires-Dist: requests>=2.22,<3.0
Requires-Dist: azure-devops==6.0.0b2
Requires-Dist: sqlalchemy>=1.3,<2.0
Requires-Dist: pyodbc>=4.0,<5.0
Requires-Dist: bcp>=0.3.0
Requires-Dist: sphinx>=2.4,<3.0 ; extra == "doc"
Requires-Dist: sphinx-autodoc-typehints>=1.10,<2.0 ; extra == "doc"
Requires-Dist: sphinx_rtd_theme>=0.4,<0.5 ; extra == "doc"
Requires-Dist: pytest>=5.1,<6.0 ; extra == "test"
Requires-Dist: pytest-cov>=2.7,<3.0 ; extra == "test"
Provides-Extra: doc
Provides-Extra: test
